{
    "Number": 1,
    "Words": [
        {
            "Korean":"또",
            "English":"In addition, and",
            "Roman":"",
            "Example":""
        },
        {
            "Korean":"아프다",
            "English":"hurt",
            "Roman":"",
            "Example":""
        },
        {
            "Korean":"아픕니다",
            "English":"It hurts",
            "Roman":"",
            "Example":""
        },
        {
            "Korean":"아파요",
            "English":"Sick",
            "Roman":"",
            "Example":""
        },
        {
            "Korean":"-아/어 보세요",
            "English":"try V-ing, plz V",
            "Roman":"",
            "Example":""
        },
        {
            "Korean":"읽어 보세요",
            "English":"read",
            "Roman":"",
            "Example":""
        },
        {
            "Korean":"들어 보세요",
            "English":"listen",
            "Roman":"",
            "Example":""
        },
        {
            "Korean":"-(으)세요",
            "English":"(plz) V",
            "Roman":"",
            "Example":""
        },
        {
            "Korean":"읽으세요",
            "English":"read",
            "Roman":"",
            "Example":""
        },
        {
            "Korean":"들으세요",
            "English":"listen",
            "Roman":"",
            "Example":""
        },
        {
            "Korean":"미안하다",
            "English":"Sorry",
            "Roman":"",
            "Example":""
        },
        {
            "Korean":"미안합니다",
            "English":"Sorry",
            "Roman":"",
            "Example":""
        },
        {
            "Korean":"미안해요",
            "English":"Sorry",
            "Roman":"",
            "Example":""
        },
        {
            "Korean":"자다",
            "English":"Sleep",
            "Roman":"",
            "Example":""
        },
        {
            "Korean":"잘 자요!",
            "English":"Sleep well!",
            "Roman":"",
            "Example":""
        },
        {
            "Korean":"잘 잤어요? 네, 저는 잘 잤어요",
            "English":"Did you sleep well? Yes, I slept well",
            "Roman":"",
            "Example":""
        },
        {
            "Korean":"-동-",
            "English":"-move-",
            "Roman":"",
            "Example":""
        },
        {
            "Korean":"자동차",
            "English":"automobile",
            "Roman":"",
            "Example":""
        },
        {
            "Korean":"동사",
            "English":"move (verb)",
            "Roman":"",
            "Example":""
        },
        {
            "Korean":"짜파게티를 먹었어요",
            "English":"I ate spaghetti",
            "Roman":"",
            "Example":""
        },
        {
            "Korean":"오토바이가 있어요? 네, 있어요",
            "English":"do you have a motorcycle? yes, I have it",
            "Roman":"",
            "Example":""
        },
        {
            "Korean":"회",
            "English":"raw fish",
            "Roman":"",
            "Example":""
        },
        {
            "Korean":"저는 회를 좋아해요 / 저는 회가 좋아요",
            "English":"I like raw fish",
            "Roman":"",
            "Example":""
        },
        {
            "Korean":"영화",
            "English":"Movies",
            "Roman":"",
            "Example":""
        },
        {
            "Korean":"영화를 좋아했어요? 네, 좋아했어요",
            "English":"Did you like movies? Yes, I liked it",
            "Roman":"",
            "Example":""
        },
        {
            "Korean":"눈",
            "English":"Eyes / Snow",
            "Roman":"",
            "Example":""
        },
        {
            "Korean":"눈이 예뻐요",
            "English":"Your eyes are pretty",
            "Roman":"",
            "Example":""
        },
        {
            "Korean":"저는 눈을 좋아해요",
            "English":"I like snow",
            "Roman":"",
            "Example":""
        },
        {
            "Korean":"좋다",
            "English":"Good",
            "Roman":"",
            "Example":""
        },
        {
            "Korean":"좋은 저녁!",
            "English":"Good evening!",
            "Roman":"",
            "Example":""
        },
        {
            "Korean":"좋아요!",
            "English":"Good!",
            "Roman":"",
            "Example":""
        },
        {
            "Korean":"맞다",
            "English":"right",
            "Roman":"",
            "Example":""
        },
        {
            "Korean":"맞아요?",
            "English":"right?",
            "Roman":"",
            "Example":""
        },
        {
            "Korean":"네, 맞아요",
            "English":"Yes that's right",
            "Roman":"",
            "Example":""
        },
        {
            "Korean":"안녕하다",
            "English":"-hello(lit: be happy well)-",
            "Roman":"",
            "Example":""
        },
        {
            "Korean":"안녕하십니까? / 안녕하세요?",
            "English":"hello?",
            "Roman":"",
            "Example":""
        }
    ]
}